cc_balancer/__init__.py
cc_balancer/cli_display.py
cc_balancer/config.py
cc_balancer/config_loader.py
cc_balancer/main.py
cc_balancer/providers.py
cc_balancer/router.py
cc_balancer/api/__init__.py
cc_balancer/api/websocket.py
cc_balancer/api/v1/__init__.py
cc_balancer/api/v1/dashboard.py
cc_balancer/api/v1/monitoring.py
cc_balancer/api/v1/providers.py
cc_balancer/api/v1/routing.py
cc_balancer/core/__init__.py
cc_balancer/core/metrics.py
cc_balancer/core/state.py
cc_balancer/static/index.html
cc_balancer/static/vite.svg
cc_balancer/static/assets/index-Bg90aP6A.css
cc_balancer/static/assets/index-Cyetsccl.js
cc_balancer/static/assets/vendor-Df84ff8T.js
cc_balancer-0.1.1.dist-info/METADATA
cc_balancer-0.1.1.dist-info/WHEEL
cc_balancer-0.1.1.dist-info/entry_points.txt
cc_balancer-0.1.1.dist-info/top_level.txt
cc_balancer-0.1.1.dist-info/RECORD
