Metadata-Version: 2.4
Name: cc-balancer
Version: 0.1.1
Summary: Intelligent proxy for Claude Code with automatic failover and load balancing
Author: CC-Balancer Contributors
License: MIT
Project-URL: Homepage, https://github.com/yourusername/cc-balancer
Project-URL: Documentation, https://github.com/yourusername/cc-balancer#readme
Project-URL: Repository, https://github.com/yourusername/cc-balancer
Project-URL: Issues, https://github.com/yourusername/cc-balancer/issues
Keywords: proxy,load-balancer,fastapi,claude,ai
Classifier: Development Status :: 3 - Alpha
Classifier: Intended Audience :: Developers
Classifier: License :: OSI Approved :: MIT License
Classifier: Programming Language :: Python :: 3
Classifier: Programming Language :: Python :: 3.10
Classifier: Programming Language :: Python :: 3.11
Classifier: Programming Language :: Python :: 3.12
Requires-Python: >=3.10
Requires-Dist: fastapi>=0.100.0
Requires-Dist: httpx>=0.24.0
Requires-Dist: pydantic>=2.0.0
Requires-Dist: pydantic-settings>=2.0.0
Requires-Dist: pyyaml>=6.0
Requires-Dist: uvicorn[standard]>=0.23.0
Requires-Dist: prometheus-client>=0.17.0
Requires-Dist: structlog>=23.0.0
Requires-Dist: cachetools>=5.3.0
Requires-Dist: python-multipart>=0.0.6
Requires-Dist: rich>=13.0.0
Provides-Extra: dev
Requires-Dist: pytest>=7.4.0; extra == "dev"
Requires-Dist: pytest-asyncio>=0.21.0; extra == "dev"
Requires-Dist: pytest-cov>=4.1.0; extra == "dev"
Requires-Dist: black>=23.0.0; extra == "dev"
Requires-Dist: ruff>=0.0.280; extra == "dev"
Requires-Dist: mypy>=1.5.0; extra == "dev"
Provides-Extra: oauth
Requires-Dist: authlib>=1.2.0; extra == "oauth"
Provides-Extra: monitoring
Requires-Dist: watchdog>=3.0.0; extra == "monitoring"
Provides-Extra: performance
Requires-Dist: py-spy>=0.3.14; extra == "performance"
Requires-Dist: locust>=2.15.0; extra == "performance"
